PyEasyDownloader/__init__.py
PyEasyDownloader-1.1.5.dist-info/METADATA
PyEasyDownloader-1.1.5.dist-info/WHEEL
PyEasyDownloader-1.1.5.dist-info/top_level.txt
PyEasyDownloader-1.1.5.dist-info/RECORD
