Metadata-Version: 2.1
Name: PyEasyDownloader
Version: 1.1.5
Summary: Track the file download process.
Home-page: https://github.com/SuperZombi/PyEasyDownloader
Author: Super_Zombi
Author-email: super.zombi.yt@gmail.com
License: UNKNOWN
Platform: UNKNOWN
Classifier: Programming Language :: Python :: 3
Classifier: License :: OSI Approved :: MIT License
Classifier: Operating System :: OS Independent
Requires-Python: >=3.6
